wcraas_storage/__init__.py
wcraas_storage/cli.py
wcraas_storage/config.py
wcraas_storage/wcraas_storage.py
wcraas_storage-0.1.3.dist-info/AUTHORS.rst
wcraas_storage-0.1.3.dist-info/LICENSE
wcraas_storage-0.1.3.dist-info/METADATA
wcraas_storage-0.1.3.dist-info/WHEEL
wcraas_storage-0.1.3.dist-info/entry_points.txt
wcraas_storage-0.1.3.dist-info/top_level.txt
wcraas_storage-0.1.3.dist-info/RECORD
